another_setuptools_git_version.py
another_setuptools_git_version-0.1.2.dist-info/LICENSE
another_setuptools_git_version-0.1.2.dist-info/METADATA
another_setuptools_git_version-0.1.2.dist-info/WHEEL
another_setuptools_git_version-0.1.2.dist-info/entry_points.txt
another_setuptools_git_version-0.1.2.dist-info/top_level.txt
another_setuptools_git_version-0.1.2.dist-info/RECORD
