Metadata-Version: 2.1
Name: another-setuptools-git-version
Version: 0.1.2
Summary: Automatically set package version using git tags.
Home-page: https://github.com/zdenekm/another-setuptools-git-version
Author: zdenekm
Author-email: zdenek.materna@gmail.com
License: MIT
Keywords: setuptools git version-control
Platform: UNKNOWN
Classifier: Framework :: Setuptools Plugin
Classifier: Intended Audience :: Developers
Classifier: License :: OSI Approved :: MIT License
Classifier: Programming Language :: Python :: 2
Classifier: Programming Language :: Python :: 3
Classifier: Development Status :: 5 - Production/Stable
Requires-Dist: setuptools (>=8.0)
